[
  {"date":"2026-05-12","time":"20:00","fyodor":"도창선","dmitri":"조풍래","ivan":"유승현","alyosha":"김대현","smerdy":"최석진","pianist":"조재철"},
  {"date":"2026-05-13","time":"20:00","fyodor":"김주호","dmitri":"백인태","ivan":"강정우","alyosha":"왕민수","smerdy":"강하경","pianist":"조재철"},
  {"date":"2026-05-14","time":"20:00","fyodor":"심재현","dmitri":"조풍래","ivan":"임강성","alyosha":"임태현","smerdy":"박두호","pianist":"양찬영"},
  {"date":"2026-05-15","time":"20:00","fyodor":"김주호","dmitri":"이형훈","ivan":"유승현","alyosha":"이선우","smerdy":"최석진","pianist":"양찬영"},
  {"date":"2026-05-16","time":"15:00","fyodor":"도창선","dmitri":"백인태","ivan":"강정우","alyosha":"김대현","smerdy":"강하경","pianist":"조영훈"},
  {"date":"2026-05-16","time":"19:00","fyodor":"도창선","dmitri":"이형훈","ivan":"강정우","alyosha":"왕민수","smerdy":"박두호","pianist":"조재철"},
  {"date":"2026-05-17","time":"14:00","fyodor":"심재현","dmitri":"백인태","ivan":"유승현","alyosha":"임태현","smerdy":"강하경","pianist":"조영훈"},
  {"date":"2026-05-17","time":"18:00","fyodor":"심재현","dmitri":"백인태","ivan":"임강성","alyosha":"왕민수","smerdy":"최석진","pianist":"조영훈"},
  {"date":"2026-05-19","time":"20:00","fyodor":"김주호","dmitri":"이형훈","ivan":"유승현","alyosha":"이선우","smerdy":"이준우","pianist":"조재철"},
  {"date":"2026-05-20","time":"16:00","fyodor":"심재현","dmitri":"조풍래","ivan":"강정우","alyosha":"김대현","smerdy":"박두호","pianist":"조영훈"},
  {"date":"2026-05-20","time":"20:00","fyodor":"도창선","dmitri":"조풍래","ivan":"강정우","alyosha":"왕민수","smerdy":"최석진","pianist":"조영훈"},
  {"date":"2026-05-21","time":"20:00","fyodor":"김주호","dmitri":"백인태","ivan":"임강성","alyosha":"이선우","smerdy":"강하경","pianist":"조재철"},
  {"date":"2026-05-22","time":"20:00","fyodor":"도창선","dmitri":"조풍래","ivan":"강정우","alyosha":"임태현","smerdy":"이준우","pianist":"양찬영"},
  {"date":"2026-05-23","time":"15:00","fyodor":"심재현","dmitri":"이형훈","ivan":"유승현","alyosha":"김대현","smerdy":"강하경","pianist":"조영훈"},
  {"date":"2026-05-23","time":"19:00","fyodor":"도창선","dmitri":"백인태","ivan":"임강성","alyosha":"왕민수","smerdy":"박두호","pianist":"양찬영"},
  {"date":"2026-05-24","time":"14:00","fyodor":"김주호","dmitri":"이형훈","ivan":"유승현","alyosha":"왕민수","smerdy":"최석진","pianist":"조재철"},
  {"date":"2026-05-24","time":"18:00","fyodor":"김주호","dmitri":"이형훈","ivan":"임강성","alyosha":"임태현","smerdy":"최석진","pianist":"조재철"},
  {"date":"2026-05-25","time":"14:00","fyodor":"도창선","dmitri":"백인태","ivan":"강정우","alyosha":"이선우","smerdy":"이준우","pianist":"조영훈"},
  {"date":"2026-05-25","time":"18:00","fyodor":"심재현","dmitri":"백인태","ivan":"강정우","alyosha":"임태현","smerdy":"강하경","pianist":"양찬영"},
  {"date":"2026-05-27","time":"16:00","fyodor":"심재현","dmitri":"조풍래","ivan":"유승현","alyosha":"김대현","smerdy":"박두호","pianist":"조영훈"},
  {"date":"2026-05-27","time":"20:00","fyodor":"김주호","dmitri":"이형훈","ivan":"임강성","alyosha":"왕민수","smerdy":"강하경","pianist":"조영훈"},
  {"date":"2026-05-28","time":"20:00","fyodor":"김주호","dmitri":"백인태","ivan":"유승현","alyosha":"임태현","smerdy":"최석진","pianist":"조재철"},
  {"date":"2026-05-29","time":"20:00","fyodor":"심재현","dmitri":"조풍래","ivan":"임강성","alyosha":"이선우","smerdy":"이준우","pianist":"양찬영"},
  {"date":"2026-05-30","time":"15:00","fyodor":"도창선","dmitri":"이형훈","ivan":"강정우","alyosha":"왕민수","smerdy":"박두호","pianist":"조재철"},
  {"date":"2026-05-30","time":"19:00","fyodor":"김주호","dmitri":"이형훈","ivan":"강정우","alyosha":"왕민수","smerdy":"이준우","pianist":"조재철"},
  {"date":"2026-05-31","time":"14:00","fyodor":"심재현","dmitri":"백인태","ivan":"임강성","alyosha":"김대현","smerdy":"최석진","pianist":"조영훈"},
  {"date":"2026-05-31","time":"18:00","fyodor":"도창선","dmitri":"백인태","ivan":"유승현","alyosha":"이선우","smerdy":"강하경","pianist":"양찬영"},
  {"date":"2026-06-02","time":"20:00","fyodor":"도창선","dmitri":"조풍래","ivan":"강정우","alyosha":"왕민수","smerdy":"강하경","pianist":"조영훈"},
  {"date":"2026-06-03","time":"14:00","fyodor":"심재현","dmitri":"백인태","ivan":"유승현","alyosha":"이선우","smerdy":"박두호","pianist":"양찬영"},
  {"date":"2026-06-03","time":"18:00","fyodor":"김주호","dmitri":"백인태","ivan":"유승현","alyosha":"임태현","smerdy":"이준우","pianist":"양찬영"},
  {"date":"2026-06-04","time":"20:00","fyodor":"심재현","dmitri":"이형훈","ivan":"강정우","alyosha":"임태현","smerdy":"이준우","pianist":"조재철"},
  {"date":"2026-06-05","time":"20:00","fyodor":"김주호","dmitri":"백인태","ivan":"임강성","alyosha":"왕민수","smerdy":"강하경","pianist":"조영훈"},
  {"date":"2026-06-06","time":"15:00","fyodor":"도창선","dmitri":"이형훈","ivan":"유승현","alyosha":"김대현","smerdy":"최석진","pianist":"조재철"},
  {"date":"2026-06-06","time":"19:00","fyodor":"김주호","dmitri":"백인태","ivan":"임강성","alyosha":"왕민수","smerdy":"최석진","pianist":"양찬영"},
  {"date":"2026-06-07","time":"14:00","fyodor":"도창선","dmitri":"조풍래","ivan":"강정우","alyosha":"임태현","smerdy":"박두호","pianist":"조영훈"},
  {"date":"2026-06-07","time":"18:00","fyodor":"심재현","dmitri":"조풍래","ivan":"강정우","alyosha":"김대현","smerdy":"강하경","pianist":"조영훈"},
  {"date":"2026-06-09","time":"20:00","fyodor":"도창선","dmitri":"조풍래","ivan":"유승현","alyosha":"왕민수","smerdy":"최석진","pianist":"양찬영"},
  {"date":"2026-06-10","time":"16:00","fyodor":"김주호","dmitri":"이형훈","ivan":"강정우","alyosha":"임태현","smerdy":"박두호","pianist":"조재철"},
  {"date":"2026-06-10","time":"20:00","fyodor":"도창선","dmitri":"백인태","ivan":"임강성","alyosha":"왕민수","smerdy":"강하경","pianist":"조재철"},
  {"date":"2026-06-11","time":"20:00","fyodor":"심재현","dmitri":"백인태","ivan":"유승현","alyosha":"왕민수","smerdy":"이준우","pianist":"양찬영"},
  {"date":"2026-06-12","time":"20:00","fyodor":"김주호","dmitri":"조풍래","ivan":"강정우","alyosha":"임태현","smerdy":"이준우","pianist":"양찬영"},
  {"date":"2026-06-13","time":"15:00","fyodor":"도창선","dmitri":"백인태","ivan":"임강성","alyosha":"이선우","smerdy":"최석진","pianist":"조영훈"},
  {"date":"2026-06-13","time":"19:00","fyodor":"심재현","dmitri":"백인태","ivan":"임강성","alyosha":"김대현","smerdy":"박두호","pianist":"양찬영"},
  {"date":"2026-06-14","time":"14:00","fyodor":"김주호","dmitri":"이형훈","ivan":"유승현","alyosha":"임태현","smerdy":"강하경","pianist":"조재철"},
  {"date":"2026-06-14","time":"18:00","fyodor":"김주호","dmitri":"조풍래","ivan":"강정우","alyosha":"왕민수","smerdy":"이준우","pianist":"조재철"},
  {"date":"2026-06-16","time":"20:00","fyodor":"김주호","dmitri":"백인태","ivan":"강정우","alyosha":"왕민수","smerdy":"이준우","pianist":"조영훈"},
  {"date":"2026-06-17","time":"16:00","fyodor":"도창선","dmitri":"조풍래","ivan":"유승현","alyosha":"왕민수","smerdy":"최석진","pianist":"조영훈"},
  {"date":"2026-06-17","time":"20:00","fyodor":"심재현","dmitri":"조풍래","ivan":"강정우","alyosha":"임태현","smerdy":"최석진","pianist":"조영훈"},
  {"date":"2026-06-18","time":"20:00","fyodor":"도창선","dmitri":"조풍래","ivan":"김재범","alyosha":"이선우","smerdy":"이준우","pianist":"조재철"},
  {"date":"2026-06-19","time":"20:00","fyodor":"심재현","dmitri":"백인태","ivan":"김재범","alyosha":"왕민수","smerdy":"박두호","pianist":"양찬영"},
  {"date":"2026-06-20","time":"15:00","fyodor":"김주호","dmitri":"조풍래","ivan":"유승현","alyosha":"김대현","smerdy":"이준우","pianist":"조영훈"},
  {"date":"2026-06-20","time":"19:00","fyodor":"도창선","dmitri":"이형훈","ivan":"김재범","alyosha":"임태현","smerdy":"강하경","pianist":"조영훈"},
  {"date":"2026-06-21","time":"14:00","fyodor":"김주호","dmitri":"백인태","ivan":"임강성","alyosha":"왕민수","smerdy":"최석진","pianist":"조재철"},
  {"date":"2026-06-21","time":"18:00","fyodor":"김주호","dmitri":"백인태","ivan":"강정우","alyosha":"왕민수","smerdy":"최석진","pianist":"양찬영"},
  {"date":"2026-06-23","time":"20:00","fyodor":"김주호","dmitri":"조풍래","ivan":"유승현","alyosha":"임태현","smerdy":"박두호","pianist":"조영훈"},
  {"date":"2026-06-24","time":"16:00","fyodor":"심재현","dmitri":"백인태","ivan":"김재범","alyosha":"왕민수","smerdy":"최석진","pianist":"조재철"},
  {"date":"2026-06-24","time":"20:00","fyodor":"심재현","dmitri":"조풍래","ivan":"강정우","alyosha":"왕민수","smerdy":"이준우","pianist":"조영훈"},
  {"date":"2026-06-25","time":"20:00","fyodor":"김주호","dmitri":"이형훈","ivan":"임강성","alyosha":"이선우","smerdy":"강하경","pianist":"조재철"},
  {"date":"2026-06-26","time":"20:00","fyodor":"김주호","dmitri":"조풍래","ivan":"김재범","alyosha":"김대현","smerdy":"이준우","pianist":"조영훈"},
  {"date":"2026-06-27","time":"15:00","fyodor":"심재현","dmitri":"백인태","ivan":"유승현","alyosha":"왕민수","smerdy":"이준우","pianist":"조재철"},
  {"date":"2026-06-27","time":"19:00","fyodor":"도창선","dmitri":"백인태","ivan":"김재범","alyosha":"왕민수","smerdy":"강하경","pianist":"양찬영"},
  {"date":"2026-06-28","time":"14:00","fyodor":"김주호","dmitri":"조풍래","ivan":"유승현","alyosha":"임태현","smerdy":"최석진","pianist":"조재철"},
  {"date":"2026-06-28","time":"18:00","fyodor":"김주호","dmitri":"조풍래","ivan":"강정우","alyosha":"김대현","smerdy":"최석진","pianist":"조재철"},
  {"date":"2026-06-30","time":"20:00","fyodor":"심재현","dmitri":"백인태","ivan":"김재범","alyosha":"왕민수","smerdy":"강하경","pianist":"조영훈"},
  {"date":"2026-07-01","time":"16:00","fyodor":"도창선","dmitri":"조풍래","ivan":"강정우","alyosha":"김대현","smerdy":"이준우","pianist":"조재철"},
  {"date":"2026-07-01","time":"20:00","fyodor":"김주호","dmitri":"조풍래","ivan":"유승현","alyosha":"왕민수","smerdy":"박두호","pianist":"조영훈"},
  {"date":"2026-07-02","time":"20:00","fyodor":"김주호","dmitri":"백인태","ivan":"유승현","alyosha":"임태현","smerdy":"최석진","pianist":"조영훈"},
  {"date":"2026-07-03","time":"20:00","fyodor":"도창선","dmitri":"백인태","ivan":"임강성","alyosha":"왕민수","smerdy":"이준우","pianist":"조영훈"},
  {"date":"2026-07-04","time":"15:00","fyodor":"김주호","dmitri":"이형훈","ivan":"김재범","alyosha":"이선우","smerdy":"최석진","pianist":"조재철"},
  {"date":"2026-07-04","time":"19:00","fyodor":"김주호","dmitri":"이형훈","ivan":"강정우","alyosha":"임태현","smerdy":"최석진","pianist":"조재철"},
  {"date":"2026-07-05","time":"14:00","fyodor":"심재현","dmitri":"백인태","ivan":"유승현","alyosha":"왕민수","smerdy":"강하경","pianist":"양찬영"},
  {"date":"2026-07-05","time":"18:00","fyodor":"심재현","dmitri":"백인태","ivan":"김재범","alyosha":"왕민수","smerdy":"박두호","pianist":"양찬영"},
  {"date":"2026-07-07","time":"20:00","fyodor":"김주호","dmitri":"조풍래","ivan":"강정우","alyosha":"왕민수","smerdy":"최석진","pianist":"조재철"},
  {"date":"2026-07-08","time":"16:00","fyodor":"도창선","dmitri":"조풍래","ivan":"유승현","alyosha":"김대현","smerdy":"이준우","pianist":"조영훈"},
  {"date":"2026-07-08","time":"20:00","fyodor":"심재현","dmitri":"조풍래","ivan":"김재범","alyosha":"왕민수","smerdy":"이준우","pianist":"조영훈"},
  {"date":"2026-07-09","time":"20:00","fyodor":"김주호","dmitri":"이형훈","ivan":"강정우","alyosha":"왕민수","smerdy":"강하경","pianist":"조영훈"},
  {"date":"2026-07-10","time":"20:00","fyodor":"도창선","dmitri":"조풍래","ivan":"김재범","alyosha":"임태현","smerdy":"최석진","pianist":"양찬영"},
  {"date":"2026-07-11","time":"15:00","fyodor":"김주호","dmitri":"백인태","ivan":"임강성","alyosha":"왕민수","smerdy":"이준우","pianist":"조재철"},
  {"date":"2026-07-11","time":"19:00","fyodor":"김주호","dmitri":"백인태","ivan":"강정우","alyosha":"왕민수","smerdy":"박두호","pianist":"조재철"},
  {"date":"2026-07-12","time":"14:00","fyodor":"심재현","dmitri":"조풍래","ivan":"김재범","alyosha":"김대현","smerdy":"최석진","pianist":"조영훈"},
  {"date":"2026-07-12","time":"18:00","fyodor":"도창선","dmitri":"조풍래","ivan":"유승현","alyosha":"임태현","smerdy":"강하경","pianist":"양찬영"},
  {"date":"2026-07-14","time":"20:00","fyodor":"김주호","dmitri":"서승원","ivan":"임강성","alyosha":"왕민수","smerdy":"이준우","pianist":"조영훈"},
  {"date":"2026-07-15","time":"16:00","fyodor":"김주호","dmitri":"조풍래","ivan":"유승현","alyosha":"이선우","smerdy":"최석진","pianist":"조재철"},
  {"date":"2026-07-15","time":"20:00","fyodor":"김주호","dmitri":"서승원","ivan":"안재영","alyosha":"김지철","smerdy":"최석진","pianist":"조재철"},
  {"date":"2026-07-16","time":"20:00","fyodor":"심재현","dmitri":"양승리","ivan":"김재범","alyosha":"김지철","smerdy":"강하경","pianist":"조영훈"},
  {"date":"2026-07-17","time":"14:00","fyodor":"도창선","dmitri":"서승원","ivan":"임강성","alyosha":"김대현","smerdy":"박두호","pianist":"조영훈"},
  {"date":"2026-07-17","time":"18:00","fyodor":"도창선","dmitri":"서승원","ivan":"유승현","alyosha":"이선우","smerdy":"강하경","pianist":"조영훈"},
  {"date":"2026-07-18","time":"15:00","fyodor":"심재현","dmitri":"조풍래","ivan":"김재범","alyosha":"왕민수","smerdy":"최석진","pianist":"양찬영"},
  {"date":"2026-07-18","time":"19:00","fyodor":"도창선","dmitri":"서승원","ivan":"유승현","alyosha":"이선우","smerdy":"강하경","pianist":"조영훈"},
  {"date":"2026-07-19","time":"14:00","fyodor":"심재현","dmitri":"양승리","ivan":"임강성","alyosha":"김지철","smerdy":"이준우","pianist":"조재철"},
  {"date":"2026-07-19","time":"18:00","fyodor":"심재현","dmitri":"양승리","ivan":"안재영","alyosha":"김지철","smerdy":"박두호","pianist":"조재철"},
  {"date":"2026-07-21","time":"20:00","fyodor":"도창선","dmitri":"서승원","ivan":"안재영","alyosha":"김대현","smerdy":"최석진","pianist":"조영훈"},
  {"date":"2026-07-22","time":"16:00","fyodor":"심재현","dmitri":"조풍래","ivan":"김재범","alyosha":"김지철","smerdy":"이준우","pianist":"조영훈"},
  {"date":"2026-07-22","time":"20:00","fyodor":"김주호","dmitri":"양승리","ivan":"안재영","alyosha":"왕민수","smerdy":"강하경","pianist":"조영훈"},
  {"date":"2026-07-23","time":"20:00","fyodor":"심재현","dmitri":"조풍래","ivan":"임강성","alyosha":"김지철","smerdy":"박두호","pianist":"조영훈"},
  {"date":"2026-07-24","time":"20:00","fyodor":"도창선","dmitri":"서승원","ivan":"김재범","alyosha":"이선우","smerdy":"최석진","pianist":"조재철"},
  {"date":"2026-07-25","time":"15:00","fyodor":"김주호","dmitri":"조풍래","ivan":"임강성","alyosha":"김대현","smerdy":"박두호","pianist":"조재철"},
  {"date":"2026-07-25","time":"19:00","fyodor":"김주호","dmitri":"조풍래","ivan":"김재범","alyosha":"이선우","smerdy":"강하경","pianist":"조재철"},
  {"date":"2026-07-26","time":"14:00","fyodor":"도창선","dmitri":"양승리","ivan":"임강성","alyosha":"김지철","smerdy":"최석진","pianist":"양찬영"},
  {"date":"2026-07-26","time":"18:00","fyodor":"심재현","dmitri":"양승리","ivan":"유승현","alyosha":"김지철","smerdy":"최석진","pianist":"조재철"}
]
